m3_fias/__init__.py
m3_fias/app_meta.py
m3_fias/constants.py
m3_fias/data.py
m3_fias/ui.py
m3_fias/utils.py
m3_fias/backends/__init__.py
m3_fias/backends/base.py
m3_fias/backends/django_rest_fias/__init__.py
m3_fias/backends/django_rest_fias/proxy/__init__.py
m3_fias/backends/django_rest_fias/proxy/actions.py
m3_fias/backends/django_rest_fias/proxy/server.py
m3_fias/backends/django_rest_fias/proxy/utils.py
m3_fias/static/m3/js/fias/AddressPanel.js
m3_fias-1.2.5.dist-info/LICENSE
m3_fias-1.2.5.dist-info/METADATA
m3_fias-1.2.5.dist-info/WHEEL
m3_fias-1.2.5.dist-info/dependency_links.txt
m3_fias-1.2.5.dist-info/top_level.txt
m3_fias-1.2.5.dist-info/RECORD
