Metadata-Version: 2.1
Name: m3-fias
Version: 1.2.5
Summary: Федеральная информационная адресная система
Home-page: https://github.com/barsgroup/m3-fias
Author: BARS Group
Author-email: bars@bars-open.ru
License: MIT
Platform: UNKNOWN
Classifier: Intended Audience :: Developers
Classifier: Environment :: Web Environment
Classifier: Natural Language :: Russian
Classifier: Operating System :: OS Independent
Classifier: Programming Language :: Python
Classifier: Programming Language :: Python :: 2.7
Classifier: Programming Language :: Python :: 3.6
Classifier: Development Status :: 5 - Production/Stable
Classifier: Framework :: Django :: 1.4
Classifier: Framework :: Django :: 1.5
Classifier: Framework :: Django :: 1.6
Classifier: Framework :: Django :: 1.7
Classifier: Framework :: Django :: 1.8
Classifier: Framework :: Django :: 1.9
Classifier: Framework :: Django :: 1.10
Classifier: Framework :: Django :: 1.11
License-File: LICENSE
Requires-Dist: six (<2,>=1.11)
Requires-Dist: requests (<3,>=2)
Requires-Dist: django (<2.3,>=1.4)
Requires-Dist: m3-core (<4,>=2.2.16)
Requires-Dist: m3-ui (<3,>=2.0.8)
Provides-Extra: oauth2
Requires-Dist: oauthlib (<3,>=2) ; extra == 'oauth2'
Requires-Dist: requests-oauthlib (<1) ; extra == 'oauth2'
